aes128/EncryptUtil.py
aes128/__init__.py
aes128_encrypt_emotibot-0.0.7.dist-info/LICENSE
aes128_encrypt_emotibot-0.0.7.dist-info/METADATA
aes128_encrypt_emotibot-0.0.7.dist-info/WHEEL
aes128_encrypt_emotibot-0.0.7.dist-info/top_level.txt
aes128_encrypt_emotibot-0.0.7.dist-info/RECORD
