Metadata-Version: 2.1
Name: aes128-encrypt-emotibot
Version: 0.0.7
Summary: AES encrypt util
Home-page: UNKNOWN
Author: Emotibot
Author-email: admin@emotibot.com
License: UNKNOWN
Platform: UNKNOWN
Requires-Dist: pycryptodomex
